setup.py
ScaleIO_py.egg-info/PKG-INFO
ScaleIO_py.egg-info/SOURCES.txt
ScaleIO_py.egg-info/dependency_links.txt
ScaleIO_py.egg-info/requires.txt
ScaleIO_py.egg-info/top_level.txt
scaleiopy/__init__.py
scaleiopy/check_im_status.py
scaleiopy/im.py
scaleiopy/installerfsm.py
scaleiopy/scaleio.py
scaleiopy/scaleioobject.py