Metadata-Version: 1.1
Name: ScaleIO-py
Version: 0.3.3-3
Summary: Python interface to ScaleIO 1.31+ REST API
Home-page: https://github.com/swevm/scaleio-py/
Author: Magnus Nilsson
Author-email: magnus@karabas.nu
License: Apache License
Platform: UNKNOWN
Classifier: Development Status :: 4 - Beta
Classifier: Intended Audience :: Developers
Classifier: Operating System :: OS Independent
Classifier: Programming Language :: Python
Classifier: Topic :: Software Development :: Libraries
Classifier: Topic :: Software Development :: Libraries :: Python Modules
